COPYING.txt
MANIFEST.in
setup.py
bin/fastac
fastac/__init__.py
fastac/compilefasta.py
fastac/sequtils.py
fastac/translationtables.py
fastac.egg-info/PKG-INFO
fastac.egg-info/SOURCES.txt
fastac.egg-info/dependency_links.txt
fastac.egg-info/not-zip-safe
fastac.egg-info/top_level.txt