Metadata-Version: 1.1
Name: fastac
Version: 0.2
Summary: Compiler for FASTA files and a FASTA-based DNA scripting language.
Home-page: https://gitorious.org/fastac/fastac
Author: Cathal Garvey
Author-email: cathalgarvey@cathalgarvey.me
License: GNU Affero General Public License v3
Platform: any
Classifier: License :: OSI Approved :: GNU Affero General Public License v3 or later (AGPLv3+)
Classifier: Development Status :: 3 - Alpha
Classifier: Operating System :: OS Independent
Classifier: Intended Audience :: Science/Research
Classifier: Topic :: Scientific/Engineering :: Bio-Informatics
Classifier: Topic :: Utilities
Classifier: Environment :: Console
Classifier: Natural Language :: English
Classifier: Programming Language :: Python
Classifier: Programming Language :: Python :: 3
Classifier: Programming Language :: Python :: 3.1
Classifier: Programming Language :: Python :: 3.2
Classifier: Programming Language :: Python :: 3.3
